<?xml version="1.0" encoding="UTF-8"?>
<databaseChangeLog
    xmlns="http://www.liquibase.org/xml/ns/dbchangelog"
    xmlns:xsi="http://www.w3.org/2001/XMLSchema-instance"
    xsi:schemaLocation="http://www.liquibase.org/xml/ns/dbchangelog
        http://www.liquibase.org/xml/ns/dbchangelog/dbchangelog-4.3.xsd">

    <changeSet id="20251108025302-insert-general-category" author="system">
        <preConditions onFail="MARK_RAN">
            <sqlCheck expectedResult="0">
                SELECT COUNT(*) FROM categories WHERE name = 'General'
            </sqlCheck>
        </preConditions>
        <insert tableName="categories">
            <column name="id" valueComputed="'00000000-0000-0000-0000-000000000001'::uuid"/>
            <column name="name" value="General"/>
            <column name="description" value="Default category for topics without a specific category"/>
            <column name="category_type" value="System"/>
            <column name="display_order" valueNumeric="0"/>
            <column name="is_active" valueBoolean="true"/>
            <column name="is_deleted" valueBoolean="false"/>
        </insert>
    </changeSet>

</databaseChangeLog>

